MANIFEST.in
README.rst
requirements.txt
setup.py
fs_hash/__init__.py
fs_hash/fs_hash.py
fs_hash.egg-info/PKG-INFO
fs_hash.egg-info/SOURCES.txt
fs_hash.egg-info/dependency_links.txt
fs_hash.egg-info/top_level.txt
requirements/common.txt