Metadata-Version: 1.2
Name: fs-hash
Version: 0.0.8
Summary: UNKNOWN
Home-page: UNKNOWN
Author: di-dip-unistra
Author-email: dnum-dip@unistra.fr
Maintainer: dnum-dip-unistra
Maintainer-email: dnum-dip@unistra.fr
License: PSF
Keywords: hash,Université de Strasbourg
Platform: UNKNOWN
